[
[
  {
    "category": "Reaction",
    "score": 80,
    "icon": "/icon-reaction.svg"
  },
  {
    "category": "Memory",
    "score": 92,
    "icon": "/icon-memory.svg"
  },
  {
    "category": "Verbal",
    "score": 61,
    "icon": "/icon-verbal.svg"
  },
  {
    "category": "Visual",
    "score": 72,
    "icon": "/icon-visual.svg"
  }
],
[
  {
    "category": "Reaction",
    "score": 45,
    "icon": "/icon-reaction.svg"
  },
  {
    "category": "Memory",
    "score": 78,
    "icon": "/icon-memory.svg"
  },
  {
    "category": "Verbal",
    "score": 37,
    "icon": "/icon-verbal.svg"
  },
  {
    "category": "Visual",
    "score": 35,
    "icon": "/icon-visual.svg"
  }
],
[
  {
    "category": "Reaction",
    "score":89,
    "icon": "/icon-reaction.svg"
  },
  {
    "category": "Memory",
    "score": 99,
    "icon": "/icon-memory.svg"
  },
  {
    "category": "Verbal",
    "score": 95,
    "icon": "/icon-verbal.svg"
  },
  {
    "category": "Visual",
    "score": 97,
    "icon": "/icon-visual.svg"
  }
],
[
  {
    "category": "Reaction",
    "score":19,
    "icon": "/icon-reaction.svg"
  },
  {
    "category": "Memory",
    "score": 39,
    "icon": "/icon-memory.svg"
  },
  {
    "category": "Verbal",
    "score": 25,
    "icon": "/icon-verbal.svg"
  },
  {
    "category": "Visual",
    "score": 17,
    "icon": "/icon-visual.svg"
  }
]
]
